{
 "po_no": "PO-2025-0021",
 "po_date": "2025-05-31",
 "buyer": {
  "code": "DIST-NO-049",
  "city": "Shillong",
  "state": "Meghalaya",
  "gstin": "23SYNTH6855F1Z2"
 },
 "seller": {
  "name": "DS Foods (SYNTHETIC) Pvt Ltd",
  "addr": "Plot 12, Sector 67, Noida, Uttar Pradesh 201301",
  "gstin": "09SYNTH2345D1Z7",
  "fssai": "10024999000123",
  "state": "Uttar Pradesh"
 },
 "lines": [
  {
   "sku": "DS-SNACNOT-029",
   "description": "NotJustNuts Almond (100g / 600ml)",
   "hsn": "2008",
   "qty": 576,
   "unit_price": 15.2
  },
  {
   "sku": "DS-SNACSNA-110",
   "description": "SnackFactory Namkeen (100g / 600ml)",
   "hsn": "2008",
   "qty": 528,
   "unit_price": 15.2
  }
 ]
}